age/__init__.py
age/__main__.py
age_2020-1.0.0.dist-info/LICENSE
age_2020-1.0.0.dist-info/METADATA
age_2020-1.0.0.dist-info/WHEEL
age_2020-1.0.0.dist-info/entry_points.txt
age_2020-1.0.0.dist-info/top_level.txt
age_2020-1.0.0.dist-info/RECORD
