Metadata-Version: 2.1
Name: age-2020
Version: 1.0.0
Summary: Gives your current age
Home-page: https://github.com/priya-mal/age_2020
Author: Priya_mal
Author-email: mv.priyanka18@gmail.com
License: MIT
Platform: UNKNOWN
Classifier: License :: OSI Approved :: MIT License
Classifier: Programming Language :: Python :: 3.6
Classifier: Programming Language :: Python :: 3.7
Classifier: Programming Language :: Python :: 3.8
